memorer/__init__.py
memorer/_config.py
memorer/_http.py
memorer/client.py
memorer/errors.py
memorer/py.typed
memorer/resources/__init__.py
memorer/resources/_base.py
memorer/resources/entities.py
memorer/resources/graph.py
memorer/resources/knowledge.py
memorer/resources/memories.py
memorer/types/__init__.py
memorer/types/common.py
memorer/types/entities.py
memorer/types/knowledge.py
memorer/types/memories.py
memorer-0.4.0.dist-info/METADATA
memorer-0.4.0.dist-info/WHEEL
memorer-0.4.0.dist-info/licenses/LICENSE
memorer-0.4.0.dist-info/RECORD
