Metadata-Version: 2.4
Name: memorer
Version: 0.4.0
Summary: Semantic memory for conversational AI - remember, recall, forget. Sub-100ms retrieval with emotional ranking and graph reasoning.
Project-URL: Homepage, https://memorer.ai
Project-URL: Documentation, https://docs.memorer.ai
Project-URL: Repository, https://github.com/memorer/memorer-python
Project-URL: Issues, https://github.com/memorer/memorer-python/issues
Project-URL: Changelog, https://github.com/memorer/memorer-python/releases
Author-email: Memorer Team <hello@memorer.ai>
License: Apache-2.0
License-File: LICENSE
Keywords: ai,chatbot,conversational-ai,knowledge-graph,llm,memory,multi-tenant,rag,retrieval,semantic-search
Classifier: Development Status :: 4 - Beta
Classifier: Intended Audience :: Developers
Classifier: License :: OSI Approved :: Apache Software License
Classifier: Operating System :: OS Independent
Classifier: Programming Language :: Python :: 3
Classifier: Programming Language :: Python :: 3.9
Classifier: Programming Language :: Python :: 3.10
Classifier: Programming Language :: Python :: 3.11
Classifier: Programming Language :: Python :: 3.12
Classifier: Programming Language :: Python :: 3.13
Classifier: Topic :: Scientific/Engineering :: Artificial Intelligence
Classifier: Topic :: Software Development :: Libraries :: Python Modules
Classifier: Typing :: Typed
Requires-Python: >=3.9
Requires-Dist: httpx>=0.24.0
Requires-Dist: pydantic>=2.0.0
Provides-Extra: dev
Requires-Dist: mypy>=1.0.0; extra == 'dev'
Requires-Dist: pytest-asyncio>=0.21.0; extra == 'dev'
Requires-Dist: pytest-cov>=4.0.0; extra == 'dev'
Requires-Dist: pytest>=7.0.0; extra == 'dev'
Requires-Dist: ruff>=0.1.0; extra == 'dev'
